keno/keno_app.py
kenoAPI-4.9.0.dist-info/LICENSE
kenoAPI-4.9.0.dist-info/METADATA
kenoAPI-4.9.0.dist-info/WHEEL
kenoAPI-4.9.0.dist-info/top_level.txt
kenoAPI-4.9.0.dist-info/RECORD
