Metadata-Version: 2.1
Name: kenoAPI
Version: 4.9.0
Summary: Python-based API used to fetch real-time and historical data from the Australian Keno website.
Home-page: https://github.com/JGolafshan/KenoAPI
Author: Joshua David Golafshan
Keywords: keno API,keno,algo,algobetting,API,betting
Classifier: Programming Language :: Python :: 3
Classifier: Operating System :: OS Independent
License-File: LICENSE
Requires-Dist: datetime
Requires-Dist: pandas
Requires-Dist: requests
Requires-Dist: flatten-dict
Requires-Dist: dateutil
Requires-Dist: cereja
